variant_json_file_utils/__init__.py
variant_json_file_utils/console_helper.py
variant_json_file_utils/constants.py
variant_json_file_utils/file_utils.py
variant_json_file_utils/system_caller.py
variant_json_file_utils/json/__init__.py
variant_json_file_utils/json/annotated_match_call/__init__.py
variant_json_file_utils/json/annotated_match_call/record.py
variant_json_file_utils/json/file/__init__.py
variant_json_file_utils/json/file/parser.py
variant_json_file_utils/json/metadata/__init__.py
variant_json_file_utils/json/metadata/parser.py
variant_json_file_utils/json/metadata/record.py
variant_json_file_utils-0.1.13.dist-info/AUTHORS.rst
variant_json_file_utils-0.1.13.dist-info/METADATA
variant_json_file_utils-0.1.13.dist-info/WHEEL
variant_json_file_utils-0.1.13.dist-info/top_level.txt
variant_json_file_utils-0.1.13.dist-info/RECORD
