Metadata-Version: 2.1
Name: variant_json_file_utils
Version: 0.1.13
Summary: Collection of Python utils for managing and processing variant JSON files.
Home-page: https://github.com/rusty-bioinfo-se/variant-json-file-utils
Author: Jaideep Sundaram
Author-email: sundaram.baylorgenetics@gmail.com
Keywords: variant_json_file_utils
Classifier: Development Status :: 2 - Pre-Alpha
Classifier: Intended Audience :: Developers
Classifier: Natural Language :: English
Classifier: Programming Language :: Python :: 3
Classifier: Programming Language :: Python :: 3.6
Classifier: Programming Language :: Python :: 3.7
Classifier: Programming Language :: Python :: 3.8
Requires-Python: >=3.6
License-File: AUTHORS.rst
Requires-Dist: Click>=7.0
Requires-Dist: Pydantic
Requires-Dist: PyYAML
Requires-Dist: Rich
Requires-Dist: singleton-decorator
